btsmart/__init__ 2.py
btsmart/__init__.py
btsmart/backend_ble.py
btsmart/backend_usb 2.py
btsmart/backend_usb.py
btsmart/controller 2.py
btsmart/controller.py
btsmart/parts 2.py
btsmart/parts.py
btsmart/__pycache__/__init__.cpython-310.pyc
btsmart/__pycache__/backend_ble.cpython-310 2.pyc
btsmart/__pycache__/backend_ble.cpython-310.pyc
btsmart/__pycache__/backend_usb.cpython-310 2.pyc
btsmart/__pycache__/backend_usb.cpython-310.pyc
btsmart/__pycache__/controller.cpython-310 2.pyc
btsmart/__pycache__/controller.cpython-310.pyc
btsmart/__pycache__/parts.cpython-310 2.pyc
btsmart/__pycache__/parts.cpython-310.pyc
btsmart-0.1.10.dist-info/LICENSE.txt
btsmart-0.1.10.dist-info/METADATA
btsmart-0.1.10.dist-info/WHEEL
btsmart-0.1.10.dist-info/top_level.txt
btsmart-0.1.10.dist-info/RECORD
