Metadata-Version: 2.1
Name: btsmart
Version: 0.1.10
Summary: A package providing convenient access to the Fischertechnik BT-Smart Controller
Home-page: https://github.com/rneumann/btsmart
Author: Rainer Neumann
Author-email: Rainer Neumann <rainer.neumann@h-ka.de>
License: MIT
Project-URL: Homepage, https://github.com/rneumann/btsmart
Project-URL: Bug Tracker, https://github.com/rneumann/btsmart/issues
Classifier: Programming Language :: Python :: 3
Classifier: License :: OSI Approved :: MIT License
Classifier: Operating System :: OS Independent
Requires-Python: >=3.7
License-File: LICENSE.txt
Requires-Dist: bleak
Requires-Dist: pyftdi
